{
  "admin": {
    "passwordHash": "689a18148c5a0cec342ba5ce0dfa5be545b00d0c0c66f0f85d9edddb20a522fc"
  },
  "contacts": {
    "address": "г. Минск, ул. Панченко, 8",
    "email": "orders@bymilia.by",
    "instagram": "https://instagram.com/",
    "mapLat": 53.882715,
    "mapLon": 27.424353,
    "phone": "+375 29 000-00-00",
    "phoneRaw": "375290000000",
    "pickupHours": "9:00–18:00, по предварительной договорённости",
    "whatsapp": "375290000000",
    "wildberries": "https://www.wildberries.by/catalog/216496169/detail.aspx"
  },
  "delivery": {
    "freeCourierMinskFrom": 150,
    "freePostFrom": 50,
    "sameDayBeforeHour": 13,
    "wholesaleLeadDays": 14
  },
  "deliveryOptions": [
    {
      "hint": "Бесплатно",
      "id": "pickup",
      "label": "Самовывоз (Минск, ул. Панченко, 8)"
    },
    {
      "hint": "Бесплатно от 150 руб.",
      "id": "courier_minsk",
      "label": "Курьер по Минску"
    },
    {
      "hint": "Бесплатно от 50 руб.",
      "id": "europost",
      "label": "Почта / Европочта (Беларусь)"
    },
    {
      "hint": "Стоимость по региону, уточнит менеджер",
      "id": "cdek_rf",
      "label": "СДЭК (Россия)"
    }
  ],
  "homepage": {
    "benefits": {
      "cards": [
        {
          "icon": "♥",
          "text": "Легко надеть самостоятельно. Согревают стопы на репетиции и между номерами.",
          "title": "Для мам и дочек"
        },
        {
          "icon": "✦",
          "text": "Опт от 10 пар, прайс для скачивания. С осени — печать логотипа коллектива.",
          "title": "Для коллективов"
        },
        {
          "icon": "◎",
          "text": "Европочта бесплатно от 50 руб., курьер по Минску от 150 руб., самовывоз.",
          "title": "Доставка по РБ"
        }
      ],
      "eyebrow": "Почему By Milia",
      "lead": "Мы знаем ритм зала: быстрый разогрев, яркие цвета в раздевалке, понятный сервис для мам и тренеров.",
      "title": "Сделано с заботой о маленьких танцовщицах"
    },
    "bento": [
      {
        "num": "01",
        "text": "Мягкие сапожки для разогрева перед занятием, репетицией и между номерами — ребёнок надевает сам.",
        "title": "Согревают стопы в зале",
        "variant": "large"
      },
      {
        "num": "02",
        "text": "Шьём в Минске. Контролируем качество и сроки — розница уходит в день заказа.",
        "title": "Свое производство",
        "variant": "tall"
      },
      {
        "num": "03",
        "text": "От 10 пар для коллективов.",
        "title": "Опт",
        "variant": "accent"
      },
      {
        "num": "04",
        "text": "Также покупайте на маркетплейсе с отзывами.",
        "title": "Wildberries",
        "variant": "small"
      },
      {
        "num": "05",
        "text": "Индивидуальный дизайн на сапожках к осеннему сезону.",
        "title": "Скоро — печать для коллектива",
        "variant": "wide"
      }
    ],
    "catalogSection": {
      "eyebrow": "Коллекция",
      "lead": "Четыре модели By Milia — в шести размерах. Фото и цены с Wildberries.",
      "title": "Выберите свой цвет"
    },
    "cta": {
      "text": "Добавьте в корзину — менеджер подтвердит заказ в WhatsApp в течение рабочего дня.",
      "title": "Готовы согреть стопы?"
    },
    "hero": {
      "cardLabel": "By Milia",
      "cardSub": "Согревают · удобны · яркие в раздевалке",
      "eyebrow": "Производство в Минске · для танцев",
      "lead": "By Milia — сапожки для разогрева, которые любят мамы юных танцовщиц и тренеры коллективов по всей Беларуси.",
      "tags": [
        "Отправка до 13:00 — в тот же день",
        "6 размеров · 25–42 см"
      ],
      "titleHtml": "Тепло для стоп <em>перед</em> выходом на сцену"
    },
    "marquee": [
      "тепло",
      "уют",
      "танцы",
      "разогрев",
      "by milia"
    ],
    "steps": {
      "eyebrow": "Как заказать",
      "items": [
        {
          "text": "4 принта в каталоге и размер",
          "title": "Выберите модель"
        },
        {
          "text": "Укажите количество пар",
          "title": "Добавьте в корзину"
        },
        {
          "text": "Имя, телефон, доставка",
          "title": "Оформите заявку"
        },
        {
          "text": "Подтвердит заказ и оплату",
          "title": "Менеджер свяжется"
        }
      ],
      "lead": "Без регистрации — заявка уходит менеджеру в WhatsApp и на почту.",
      "title": "Четыре простых шага"
    }
  },
  "pages": {
    "about": {
      "html": "<p><strong>By Milia</strong> — белорусский бренд сапожек для разогрева стоп, созданный для юных танцовщиц и их мам.</p><p>Мы делаем изделия, которые помогают согреть ножки перед занятием, на репетиции и между номерами. Наши покупатели — семьи, которые живут ритмом танцевального зала, и тренеры, которые заботятся о комфорте коллектива.</p><h2>Почему By Milia</h2><ul><li>Собственное производство в Минске</li><li>Четыре расцветки и полный размерный ряд</li><li>Понятный сервис: заказ на сайте, подтверждение менеджером</li></ul>",
      "title": "О нас"
    },
    "contacts": {
      "html": "<p>Свяжитесь с нами по телефону, WhatsApp или email — контакты в подвале сайта.</p>",
      "title": "Контакты"
    },
    "delivery": {
      "html": "<p>Доставка по Беларуси — Европочта (бесплатно от 50 руб.), курьер по Минску (от 150 руб.), самовывоз с ул. Панченко, 8.</p><p>Оплата после подтверждения заказа менеджером.</p>",
      "title": "Доставка и оплата"
    },
    "faq": {
      "html": "<p>Раздел в разработке. Задайте вопрос менеджеру в WhatsApp.</p>",
      "title": "Вопросы"
    },
    "guarantee": {
      "html": "<p>Условия гарантии и возврата уточняйте у менеджера при оформлении заказа.</p>",
      "title": "Гарантия и возврат"
    },
    "news": {
      "html": "<p>Следите за обновлениями в Instagram.</p>",
      "title": "Новости"
    },
    "offer": {
      "html": "<p>Текст оферты предоставляется по запросу.</p>",
      "title": "Публичная оферта"
    },
    "privacy": {
      "html": "<p>Мы обрабатываем персональные данные только для выполнения заказа.</p>",
      "title": "Конфиденциальность"
    },
    "production": {
      "html": "<p>Шьём в Минске. Контролируем качество материалов и пошива.</p>",
      "title": "Производство"
    },
    "where-to-buy": {
      "html": "<p>На сайте, самовывоз в Минске, а также на Wildberries.</p>",
      "title": "Где купить"
    },
    "wholesale": {
      "html": "<p>Опт от 10 пар для танцевальных коллективов и студий. Напишите в WhatsApp или на почту — укажите коллектив, расцветки, размеры и количество.</p>",
      "title": "Опт"
    }
  },
  "site": {
    "brand": "By Milia",
    "currency": "BYN",
    "currencyLabel": "руб.",
    "tagline": "Сапожки для разогрева стоп для танцев"
  },
  "sizes": [
    {
      "id": "25-27",
      "label": "25–27"
    },
    {
      "id": "28-30",
      "label": "28–30"
    },
    {
      "id": "31-33",
      "label": "31–33"
    },
    {
      "id": "34-36",
      "label": "34–36"
    },
    {
      "id": "37-39",
      "label": "37–39"
    },
    {
      "id": "40-42",
      "label": "40–42"
    }
  ]
}
